sk_general/__init__.py
sk_general/data/__init__.py
sk_general/data/data_processing.py
sk_general/data/typing.py
sk_general/model/__init__.py
sk_general/model/modeling.py
sk_general/model/typing.py
sk_general-0.0.1.dist-info/WHEEL
sk_general-0.0.1.dist-info/METADATA
sk_general-0.0.1.dist-info/RECORD
