Metadata-Version: 2.1
Name: sk_general
Version: 0.0.1
Summary: A collection of packages, functions and classes used for deploying models in a unified interface.
Author-email: Iñigo Hidalgo <inigohrey@gmail.com>
Project-URL: Home, https://inigohidalgo.com/sk_general
